autoML/__init__.py
autoML/AutoDetect/__init__.py
autoML/AutoDetect/auto_detect.py
autoML/AutoDetect/vietnamese_nlp/__init__.py
autoML/AutoDetect/vietnamese_nlp/nlp_onnx.py
autoML/AutoDetect/vietnamese_nlp/vietocr/__init__.py
autoML/AutoDetect/vietnamese_nlp/vietocr/predict.py
autoML/AutoDetect/vietnamese_nlp/vietocr/train.py
autoML/AutoDetect/vietnamese_nlp/vietocr/loader/__init__.py
autoML/AutoDetect/vietnamese_nlp/vietocr/loader/aug.py
autoML/AutoDetect/vietnamese_nlp/vietocr/loader/dataloader.py
autoML/AutoDetect/vietnamese_nlp/vietocr/loader/dataloader_v1.py
autoML/AutoDetect/vietnamese_nlp/vietocr/model/__init__.py
autoML/AutoDetect/vietnamese_nlp/vietocr/model/beam.py
autoML/AutoDetect/vietnamese_nlp/vietocr/model/trainer.py
autoML/AutoDetect/vietnamese_nlp/vietocr/model/transformerocr.py
autoML/AutoDetect/vietnamese_nlp/vietocr/model/vocab.py
autoML/AutoDetect/vietnamese_nlp/vietocr/model/backbone/__init__.py
autoML/AutoDetect/vietnamese_nlp/vietocr/model/backbone/cnn.py
autoML/AutoDetect/vietnamese_nlp/vietocr/model/backbone/resnet.py
autoML/AutoDetect/vietnamese_nlp/vietocr/model/backbone/vgg.py
autoML/AutoDetect/vietnamese_nlp/vietocr/model/seqmodel/__init__.py
autoML/AutoDetect/vietnamese_nlp/vietocr/model/seqmodel/convseq2seq.py
autoML/AutoDetect/vietnamese_nlp/vietocr/model/seqmodel/seq2seq.py
autoML/AutoDetect/vietnamese_nlp/vietocr/model/seqmodel/transformer.py
autoML/AutoDetect/vietnamese_nlp/vietocr/optim/__init__.py
autoML/AutoDetect/vietnamese_nlp/vietocr/optim/labelsmoothingloss.py
autoML/AutoDetect/vietnamese_nlp/vietocr/optim/optim.py
autoML/AutoDetect/vietnamese_nlp/vietocr/tests/__init__.py
autoML/AutoDetect/vietnamese_nlp/vietocr/tests/utest.py
autoML/AutoDetect/vietnamese_nlp/vietocr/tool/__init__.py
autoML/AutoDetect/vietnamese_nlp/vietocr/tool/config.py
autoML/AutoDetect/vietnamese_nlp/vietocr/tool/create_dataset.py
autoML/AutoDetect/vietnamese_nlp/vietocr/tool/logger.py
autoML/AutoDetect/vietnamese_nlp/vietocr/tool/predictor.py
autoMLF-1.0.3.dist-info/METADATA
autoMLF-1.0.3.dist-info/WHEEL
autoMLF-1.0.3.dist-info/entry_points.txt
autoMLF-1.0.3.dist-info/top_level.txt
autoMLF-1.0.3.dist-info/RECORD
