Metadata-Version: 2.1
Name: autoMLF
Version: 1.0.3
Summary: autoML for training and inference Deep Learning model
Home-page: https://github.com/aihackervn
Author: TinVo
Author-email: tinprocoder0908@gmail.com
License: MIT
Keywords: AI HACKER VNESE,AI,autoML,Deep Learning,Computer Vision,Interface
Classifier: License :: OSI Approved :: MIT License
Classifier: Programming Language :: Python :: 3.9
Classifier: Operating System :: OS Independent
Requires-Python: >=3.9
Requires-Dist: annotated-types (==0.5.0)
Requires-Dist: anyio (==3.7.1)
Requires-Dist: beautifulsoup4 (==4.12.2)
Requires-Dist: bleach (==6.0.0)
Requires-Dist: certifi (==2023.5.7)
Requires-Dist: charset-normalizer (==3.2.0)
Requires-Dist: coloredlogs (==15.0.1)
Requires-Dist: contourpy (==1.1.0)
Requires-Dist: cycler (==0.11.0)
Requires-Dist: docutils (==0.20.1)
Requires-Dist: einops (==0.6.1)
Requires-Dist: exceptiongroup (==1.1.2)
Requires-Dist: fastapi (==0.100.0)
Requires-Dist: filelock (==3.12.2)
Requires-Dist: flatbuffers (==23.5.26)
Requires-Dist: fonttools (==4.40.0)
Requires-Dist: gdown (==4.7.1)
Requires-Dist: humanfriendly (==10.0)
Requires-Dist: idna (==3.4)
Requires-Dist: importlib-metadata (==6.8.0)
Requires-Dist: importlib-resources (==6.0.0)
Requires-Dist: jaraco.classes (==3.3.0)
Requires-Dist: Jinja2 (==3.1.2)
Requires-Dist: joblib (==1.3.1)
Requires-Dist: keyring (==24.2.0)
Requires-Dist: kiwisolver (==1.4.4)
Requires-Dist: markdown-it-py (==3.0.0)
Requires-Dist: MarkupSafe (==2.1.3)
Requires-Dist: matplotlib (==3.7.2)
Requires-Dist: mdurl (==0.1.2)
Requires-Dist: more-itertools (==9.1.0)
Requires-Dist: mpmath (==1.3.0)
Requires-Dist: networkx (==3.1)
Requires-Dist: numpy (==1.25.0)
Requires-Dist: onnxruntime (==1.15.1)
Requires-Dist: opencv-python (==4.8.0.74)
Requires-Dist: packaging (==23.1)
Requires-Dist: pandas (==2.0.3)
Requires-Dist: Pillow (==10.0.0)
Requires-Dist: pkginfo (==1.9.6)
Requires-Dist: protobuf (==4.23.4)
Requires-Dist: psutil (==5.9.5)
Requires-Dist: pydantic (==2.0.2)
Requires-Dist: pydantic-core (==2.1.2)
Requires-Dist: Pygments (==2.15.1)
Requires-Dist: pyparsing (==3.0.9)
Requires-Dist: PySocks (==1.7.1)
Requires-Dist: python-dateutil (==2.8.2)
Requires-Dist: pytz (==2023.3)
Requires-Dist: PyYAML (==6.0)
Requires-Dist: readme-renderer (==40.0)
Requires-Dist: requests (==2.31.0)
Requires-Dist: requests-toolbelt (==1.0.0)
Requires-Dist: rfc3986 (==2.0.0)
Requires-Dist: rich (==13.4.2)
Requires-Dist: scikit-learn (==1.3.0)
Requires-Dist: scipy (==1.11.1)
Requires-Dist: seaborn (==0.12.2)
Requires-Dist: six (==1.16.0)
Requires-Dist: sniffio (==1.3.0)
Requires-Dist: soupsieve (==2.4.1)
Requires-Dist: starlette (==0.27.0)
Requires-Dist: sympy (==1.12)
Requires-Dist: threadpoolctl (==3.1.0)
Requires-Dist: torch (==1.9.0)
Requires-Dist: torchvision (==0.10.0)
Requires-Dist: tqdm (==4.65.0)
Requires-Dist: twine (==4.0.2)
Requires-Dist: typing-extensions (==4.7.1)
Requires-Dist: tzdata (==2023.3)
Requires-Dist: ultralytics (==8.0.131)
Requires-Dist: urllib3 (==2.0.3)
Requires-Dist: webencodings (==0.5.1)
Requires-Dist: wget (==3.2)
Requires-Dist: zipp (==3.15.0)
Provides-Extra: dev
Requires-Dist: pytest (>=7.0) ; extra == 'dev'
Requires-Dist: twine (>=4.0.2) ; extra == 'dev'
